optoforce/__init__.py
optoforce/__main__.py
optoforce/reading.py
optoforce/status.py
optoforce-0.3.0.dist-info/entry_points.txt
optoforce-0.3.0.dist-info/LICENSE
optoforce-0.3.0.dist-info/WHEEL
optoforce-0.3.0.dist-info/METADATA
optoforce-0.3.0.dist-info/RECORD
