Metadata-Version: 2.1
Name: optoforce
Version: 0.3.0
Summary: optoforce
Home-page: https://github.com/alknemeyer/optoforce
Keywords: sensor,optoforce
Author: Alexander Knemeyer
Author-email: alknemeyer@hey.com
Requires-Python: >=3.6
Classifier: Intended Audience :: Education
Classifier: Intended Audience :: Developers
Classifier: Intended Audience :: Science/Research
Classifier: License :: OSI Approved :: MIT License
Classifier: Natural Language :: English
Classifier: Programming Language :: Python :: 3.6
Classifier: Programming Language :: Python :: 3.7
Classifier: Programming Language :: Python :: 3.8
Classifier: Programming Language :: Python :: 3.9
Classifier: Topic :: Scientific/Engineering
Classifier: Typing :: Typed
Requires-Dist: pyserial ~= 3.0
Requires-Dist: typing-extensions ~= 3.0; python_version<'3.8'
